inline_importer/__init__.py
inline_importer/__main__.py
inline_importer/_version.py
inline_importer/builder.py
inline_importer/e.py
inline_importer/importer.py
inline_importer/inline_importer.py
inline_importer/inliner.py
inline_importer-0.0.4.dist-info/LICENSE.txt
inline_importer-0.0.4.dist-info/METADATA
inline_importer-0.0.4.dist-info/WHEEL
inline_importer-0.0.4.dist-info/entry_points.txt
inline_importer-0.0.4.dist-info/top_level.txt
inline_importer-0.0.4.dist-info/RECORD
