Metadata-Version: 2.1
Name: inline-importer
Version: 0.0.4
Summary: Python module inlining library
Home-page: https://github.com/MagnaXSoftware/python-inlineimporter
Author: MagnaX Software
Author-email: info@magnax.ca
License: License :: OSI Approved :: MIT License
Platform: UNKNOWN
Classifier: Development Status :: 3 - Alpha
Classifier: Intended Audience :: Developers
Classifier: License :: OSI Approved :: MIT License
Classifier: Programming Language :: Python :: 3
Classifier: Programming Language :: Python :: 3.4
Classifier: Programming Language :: Python :: 3.5
Classifier: Programming Language :: Python :: 3.6
Classifier: Programming Language :: Python :: 3.7
Classifier: Programming Language :: Python :: 3.8
Requires-Python: ~=3.4
